Metadata-Version: 1.2
Name: Yolo2Voc
Version: 1.0.3
Summary: Yolo Annotation to PascalVOC annotation.
Home-page: https://github.com/BrWillian/Yolo2Voc/
Author: Willian Antunes
Author-email: wiliam-m-@hotmail.com
Maintainer: Willian Antunes
Maintainer-email: wiliam-m-@hotmail.com
License: MIT
Project-URL: Documentation, https://yolo2voc.readthedocs.io/
Keywords: Yolo2Voc Yolo PascalVOC
Platform: UNKNOWN
Classifier: Development Status :: 5 - Production/Stable
Classifier: Programming Language :: Python :: 3
Classifier: Programming Language :: Python :: 3.6
Classifier: Programming Language :: Python :: 3.7
Classifier: Programming Language :: Python :: 3.8
Classifier: Programming Language :: Python :: 3.9
Classifier: License :: OSI Approved :: MIT License
Requires-Python: >=3.6
